cartoGRAPHs/__init__.py
cartoGRAPHs/cartoGRAPHs.py
cartoGRAPHs/func_calculations.py
cartoGRAPHs/func_embed_plot.py
cartoGRAPHs/func_exportVR.py
cartoGRAPHs/func_load_data.py
cartoGRAPHs/func_visual_properties.py
cartoGRAPHs-2.0.1.dist-info/LICENSE.md
cartoGRAPHs-2.0.1.dist-info/METADATA
cartoGRAPHs-2.0.1.dist-info/WHEEL
cartoGRAPHs-2.0.1.dist-info/top_level.txt
cartoGRAPHs-2.0.1.dist-info/RECORD
