Metadata-Version: 2.1
Name: cartoGRAPHs
Version: 2.0.1
Summary: A Network Layout and Visualization Package
Home-page: https://github.com/menchelab/cartoGRAPHs
Author: Chris H.
Author-email: chris@menchelab.com
License: MIT License
License-File: LICENSE.md
Requires-Dist: numpy
Requires-Dist: pandas
Requires-Dist: matplotlib
Requires-Dist: seaborn
Requires-Dist: scipy
Requires-Dist: networkx
Requires-Dist: plotly
Requires-Dist: colormath
Requires-Dist: umap-learn
Requires-Dist: scikit-learn
Requires-Dist: shapely
Requires-Dist: numba
Requires-Dist: pynndescent ==0.5.8
